LICENSE
MANIFEST.in
README.md
requirements.txt
setup.py
easy_file_manager/__init__.py
easy_file_manager/easy_file_manager.py
easy_file_manager.egg-info/PKG-INFO
easy_file_manager.egg-info/SOURCES.txt
easy_file_manager.egg-info/dependency_links.txt
easy_file_manager.egg-info/entry_points.txt
easy_file_manager.egg-info/requires.txt
easy_file_manager.egg-info/top_level.txt
test/__init__.py
test/test_unittests_easy_file_selector.py