Metadata-Version: 2.1
Name: easy-file-manager
Version: 0.3
Summary: Package to easily let a user select multiple files for further use
Home-page: https://github.com/lstuma/easy_file_selector
Author: Lukas Stockmann
Author-email: g.lstuma@gmail.com
License: UNKNOWN
Platform: UNKNOWN
Classifier: Development Status :: 3 - Alpha
Classifier: Programming Language :: Python :: 3
Classifier: License :: OSI Approved :: MIT License
Classifier: Operating System :: OS Independent
Requires-Python: >=3.7
